MANIFEST.in
README.rst
setup.cfg
setup.py
docs/CREDITS.rst
docs/HISTORY.rst
docs/LICENSE.GPL
docs/LICENSE.txt
src/sc/__init__.py
src/sc.contentrules.metadata.egg-info/PKG-INFO
src/sc.contentrules.metadata.egg-info/SOURCES.txt
src/sc.contentrules.metadata.egg-info/dependency_links.txt
src/sc.contentrules.metadata.egg-info/entry_points.txt
src/sc.contentrules.metadata.egg-info/namespace_packages.txt
src/sc.contentrules.metadata.egg-info/not-zip-safe
src/sc.contentrules.metadata.egg-info/requires.txt
src/sc.contentrules.metadata.egg-info/top_level.txt
src/sc/contentrules/__init__.py
src/sc/contentrules/metadata/__init__.py
src/sc/contentrules/metadata/configure.zcml
src/sc/contentrules/metadata/testing.py
src/sc/contentrules/metadata/utils.py
src/sc/contentrules/metadata/actions/__init__.py
src/sc/contentrules/metadata/actions/configure.zcml
src/sc/contentrules/metadata/actions/contributors.py
src/sc/contentrules/metadata/actions/creators.py
src/sc/contentrules/metadata/actions/language.py
src/sc/contentrules/metadata/actions/navigation.py
src/sc/contentrules/metadata/actions/rights.py
src/sc/contentrules/metadata/actions/subject.py
src/sc/contentrules/metadata/conditions/__init__.py
src/sc/contentrules/metadata/conditions/configure.zcml
src/sc/contentrules/metadata/conditions/subject.py
src/sc/contentrules/metadata/locales/manual.pot
src/sc/contentrules/metadata/locales/plone.pot
src/sc/contentrules/metadata/locales/sc.contentrules.metadata.pot
src/sc/contentrules/metadata/locales/es/LC_MESSAGES/plone.mo
src/sc/contentrules/metadata/locales/es/LC_MESSAGES/plone.po
src/sc/contentrules/metadata/locales/es/LC_MESSAGES/sc.contentrules.metadata.mo
src/sc/contentrules/metadata/locales/es/LC_MESSAGES/sc.contentrules.metadata.po
src/sc/contentrules/metadata/locales/pt_BR/LC_MESSAGES/plone.mo
src/sc/contentrules/metadata/locales/pt_BR/LC_MESSAGES/plone.po
src/sc/contentrules/metadata/locales/pt_BR/LC_MESSAGES/sc.contentrules.metadata.mo
src/sc/contentrules/metadata/locales/pt_BR/LC_MESSAGES/sc.contentrules.metadata.po
src/sc/contentrules/metadata/tests/__init__.py
src/sc/contentrules/metadata/tests/test_action_contributors.py
src/sc/contentrules/metadata/tests/test_action_creators.py
src/sc/contentrules/metadata/tests/test_action_exclude_from_nav.py
src/sc/contentrules/metadata/tests/test_action_language.py
src/sc/contentrules/metadata/tests/test_action_rights.py
